{
	"classify01" : {
		"list" : [
					{
						"id" : "shop001",
						"firstSrc" : "banImg1.jpg",
						"name" : "怀德堂娇小君玫瑰花阿胶糕（精装）500g/盒 包邮",
						"price" : "¥155.98",
						"addr" : "中国",
						"lastSrc" : "country2.jpg"
					},
					{
						"id" : "shop002",
						"firstSrc" : "banImg2.jpg",
						"name" : "怀德堂娇小君玫瑰花阿胶糕（精装）500g/盒 包邮",
						"price" : "¥155.98",
						"addr" : "中国",
						"lastSrc" : "country2.jpg"
					},
					{
						"id" : "shop003",
						"firstSrc" : "banImg3.jpg",
						"name" : "怀德堂娇小君玫瑰花阿胶糕（精装）500g/盒 包邮",
						"price" : "¥155.98",
						"addr" : "中国",
						"lastSrc" : "country2.jpg"
					},
					{
						"id" : "shop004",
						"firstSrc" : "banImg4.jpg",
						"name" : "怀德堂娇小君玫瑰花阿胶糕（精装）500g/盒 包邮",
						"price" : "¥155.98",
						"addr" : "中国",
						"lastSrc" : "country2.jpg"
					},
					{
						"id" : "shop005",
						"firstSrc" : "banImg5.jpg",
						"name" : "怀德堂娇小君玫瑰花阿胶糕（精装）500g/盒 包邮",
						"price" : "¥155.98",
						"addr" : "中国",
						"lastSrc" : "country2.jpg"
					},
					{
						"id" : "shop006",
						"firstSrc" : "banImg6.jpg",
						"name" : "怀德堂娇小君玫瑰花阿胶糕（精装）500g/盒 包邮",
						"price" : "¥155.98",
						"addr" : "中国",
						"lastSrc" : "country2.jpg"
					},
					{
						"id" : "shop007",
						"firstSrc" : "banImg7.jpg",
						"name" : "怀德堂娇小君玫瑰花阿胶糕（精装）500g/盒 包邮",
						"price" : "¥155.98",
						"addr" : "中国",
						"lastSrc" : "country2.jpg"
					},
					{
						"id" : "shop008",
						"firstSrc" : "banImg8.jpg",
						"name" : "怀德堂娇小君玫瑰花阿胶糕（精装）500g/盒 包邮",
						"price" : "¥155.98",
						"addr" : "中国",
						"lastSrc" : "country2.jpg"
					},
					{
						"id" : "shop009",
						"firstSrc" : "banImg9.jpg",
						"name" : "怀德堂娇小君玫瑰花阿胶糕（精装）500g/盒 包邮",
						"price" : "¥155.98",
						"addr" : "中国",
						"lastSrc" : "country2.jpg"
					},
					{
						"id" : "shop010",
						"firstSrc" : "banImg10.jpg",
						"name" : "怀德堂娇小君玫瑰花阿胶糕（精装）500g/盒 包邮",
						"price" : "¥155.98",
						"addr" : "中国",
						"lastSrc" : "country2.jpg"
					},
					{
						"id" : "shop011",
						"firstSrc" : "banImg11.jpg",
						"name" : "怀德堂娇小君玫瑰花阿胶糕（精装）500g/盒 包邮",
						"price" : "¥155.98",
						"addr" : "中国",
						"lastSrc" : "country2.jpg"
					},
					{
						"id" : "shop012",
						"firstSrc" : "banImg12.jpg",
						"name" : "怀德堂娇小君玫瑰花阿胶糕（精装）500g/盒 包邮",
						"price" : "¥155.98",
						"addr" : "中国",
						"lastSrc" : "country2.jpg"
					},
					{
						"id" : "shop013",
						"firstSrc" : "banImg13.jpg",
						"name" : "怀德堂娇小君玫瑰花阿胶糕（精装）500g/盒 包邮",
						"price" : "¥155.98",
						"addr" : "中国",
						"lastSrc" : "country2.jpg"
					},
					{
						"id" : "shop014",
						"firstSrc" : "banImg14.jpg",
						"name" : "怀德堂娇小君玫瑰花阿胶糕（精装）500g/盒 包邮",
						"price" : "¥155.98",
						"addr" : "中国",
						"lastSrc" : "country2.jpg"
					},
					{
						"id" : "shop015",
						"firstSrc" : "banImg15.jpg",
						"name" : "怀德堂娇小君玫瑰花阿胶糕（精装）500g/盒 包邮",
						"price" : "¥155.98",
						"addr" : "中国",
						"lastSrc" : "country2.jpg"
					}
				]
	},
	"classify02" :{ 
		"list" : [
					{
						"id" : "shop016",
						"firstSrc" : "banImg16.jpg",
						"name" : "怀德堂娇小君玫瑰花阿胶糕（精装）500g/盒 包邮",
						"price" : "¥155.98",
						"addr" : "中国",
						"lastSrc" : "country2.jpg"
					},
					{
						"id" : "shop017",
						"firstSrc" : "banImg15.jpg",
						"name" : "怀德堂娇小君玫瑰花阿胶糕（精装）500g/盒 包邮",
						"price" : "¥155.98",
						"addr" : "中国",
						"lastSrc" : "country2.jpg"
					},
					{
						"id" : "shop018",
						"firstSrc" : "banImg16.jpg",
						"name" : "怀德堂娇小君玫瑰花阿胶糕（精装）500g/盒 包邮",
						"price" : "¥155.98",
						"addr" : "中国",
						"lastSrc" : "country2.jpg"
					},
					{
						"id" : "shop019",
						"firstSrc" : "banImg17.jpg",
						"name" : "怀德堂娇小君玫瑰花阿胶糕（精装）500g/盒 包邮",
						"price" : "¥155.98",
						"addr" : "中国",
						"lastSrc" : "country2.jpg"
					},
					{
						"id" : "shop020",
						"firstSrc" : "banImg18.jpg",
						"name" : "怀德堂娇小君玫瑰花阿胶糕（精装）500g/盒 包邮",
						"price" : "¥155.98",
						"addr" : "中国",
						"lastSrc" : "country2.jpg"
					},
					{
						"id" : "shop021",
						"firstSrc" : "banImg15.jpg",
						"name" : "怀德堂娇小君玫瑰花阿胶糕（精装）500g/盒 包邮",
						"price" : "¥155.98",
						"addr" : "中国",
						"lastSrc" : "country2.jpg"
					},
					{
						"id" : "shop022",
						"firstSrc" : "banImg15.jpg",
						"name" : "怀德堂娇小君玫瑰花阿胶糕（精装）500g/盒 包邮",
						"price" : "¥155.98",
						"addr" : "中国",
						"lastSrc" : "country2.jpg"
					},
					{
						"id" : "shop023",
						"firstSrc" : "banImg15.jpg",
						"name" : "怀德堂娇小君玫瑰花阿胶糕（精装）500g/盒 包邮",
						"price" : "¥155.98",
						"addr" : "中国",
						"lastSrc" : "country2.jpg"
					},
					{
						"id" : "shop024",
						"firstSrc" : "banImg15.jpg",
						"name" : "怀德堂娇小君玫瑰花阿胶糕（精装）500g/盒 包邮",
						"price" : "¥155.98",
						"addr" : "中国",
						"lastSrc" : "country2.jpg"
					},
					{
						"id" : "shop025",
						"firstSrc" : "banImg15.jpg",
						"name" : "怀德堂娇小君玫瑰花阿胶糕（精装）500g/盒 包邮",
						"price" : "¥155.98",
						"addr" : "中国",
						"lastSrc" : "country2.jpg"
					}
				]
	}
}

